display_out.v
module display_out(
    input wire clk,
    input wire rst,
    input wire enable,
    input wire [15:0] bcd_in,
    output wire data_out,
    output wire sending_data
);

//assign clk = HF_int_osc;


// Conversor BCD a 32 bits en segment_data
localparam [7:0] Disp_0 = 8'b11111100; // 0
localparam [7:0] Disp_1 = 8'b01100000; // 1
localparam [7:0] Disp_2 = 8'b11011010; // 2
localparam [7:0] Disp_3 = 8'b11110010; // 3
localparam [7:0] Disp_4 = 8'b01100110; // 4
localparam [7:0] Disp_5 = 8'b10110110; // 5
localparam [7:0] Disp_6 = 8'b10111110; // 6
localparam [7:0] Disp_7 = 8'b11100000; // 7
localparam [7:0] Disp_8 = 8'b11111110; // 8
localparam [7:0] Disp_9 = 8'b11110110; // 9
localparam [7:0] Error_Disp = 8'b00000010; // -

function [7:0] bcd2seg;
  input [3:0] b;
  begin
    case (b)
      4'd0: bcd2seg = Disp_0;
      4'd1: bcd2seg = Disp_1;
      4'd2: bcd2seg = Disp_2;
      4'd3: bcd2seg = Disp_3;
      4'd4: bcd2seg = Disp_4;
      4'd5: bcd2seg = Disp_5;
      4'd6: bcd2seg = Disp_6;
      4'd7: bcd2seg = Disp_7;
      4'd8: bcd2seg = Disp_8;
      4'd9: bcd2seg = Disp_9;
      default: bcd2seg = Error_Disp;
    endcase
  end
endfunction

// Calculamos internamente los 32 bits de segmentos a partir de los 4 nibbles BCD
wire [31:0] segment_data_calc;
// LSB primero
assign segment_data_calc = { bcd2seg(bcd_in[3:0]), 
                             bcd2seg(bcd_in[7:4]), 
                             bcd2seg(bcd_in[11:8]), 
                             bcd2seg(bcd_in[15:12]) }; 

// Paralelo a Serie de 32 bits

parameter [31:0] send_interval = 31'd31;
reg [31:0] interval_counter;
reg [31:0] segment_data_out;

always @(negedge clk)
    if (rst) begin
        interval_counter <= 0;
        segment_data_out <= 0; 
    end else if (enable) begin
        if (interval_counter == 0)
            segment_data_out <= segment_data_calc;
        else 
            segment_data_out <= segment_data_out >> 1;

        if (interval_counter <= send_interval)
            interval_counter <= interval_counter + 1;
        else   
            interval_counter <= 0;
        
    end

assign sending_data = (interval_counter == 31);
assign data_out = segment_data_out[0];

endmodule

display_tb.v


module dispout_tb();
    reg clk;
    reg reset;
    reg [15:0] bcd_in;
    wire data_out;
    wire sending_data;

    // Instanciación por nombre para evitar errores si cambian puertos
    display_out disp1(
        .clk(clk),
        .rst(reset),
        .enable(1'b1),
        .bcd_in(bcd_in),
        .data_out(data_out),
        .sending_data(sending_data)
    );

    initial begin
        clk <= 0;
        reset <= 1;
        bcd_in <= 16'b0010010101110001; // ejemplo de 4 nibbles
    end


    always begin
        #5 clk = ~clk;
    end

    initial begin
        $dumpfile("1.vcd");
        $dumpvars(3);
        #10 reset <= 0;

        #9000 $finish;
    end


endmodule

1.vcd
$date
	Fri Oct 24 20:14:29 2025
$end
$version
	Icarus Verilog
$end
$timescale
	1s
$end
$scope module dispout_tb $end
$var wire 1 ! sending_data $end
$var wire 1 " data_out $end
$var reg 16 # bcd_in [15:0] $end
$var reg 1 $ clk $end
$var reg 1 % reset $end
$scope module disp1 $end
$var wire 16 & bcd_in [15:0] $end
$var wire 1 $ clk $end
$var wire 1 ' enable $end
$var wire 1 % rst $end
$var wire 1 ! sending_data $end
$var wire 32 ( segment_data_calc [31:0] $end
$var wire 1 " data_out $end
$var parameter 8 ) Disp_0 $end
$var parameter 8 * Disp_1 $end
$var parameter 8 + Disp_2 $end
$var parameter 8 , Disp_3 $end
$var parameter 8 - Disp_4 $end
$var parameter 8 . Disp_5 $end
$var parameter 8 / Disp_6 $end
$var parameter 8 0 Disp_7 $end
$var parameter 8 1 Disp_8 $end
$var parameter 8 2 Disp_9 $end
$var parameter 8 3 Error_Disp $end
$var parameter 32 4 send_interval $end
$var reg 32 5 interval_counter [31:0] $end
$var reg 32 6 segment_data_out [31:0] $end
$scope function bcd2seg $end
$var reg 4 7 b [3:0] $end
$upscope $end
$upscope $end
$upscope $end
$enddefinitions $end
$comment Show the parameter values. $end
$dumpall
b11111 4
b10 3
b11110110 2
b11111110 1
b11100000 0
b10111110 /
b10110110 .
b1100110 -
b11110010 ,
b11011010 +
b1100000 *
b11111100 )
$end
#0
$dumpvars
b1 7
b0 6
b0 5
b1100000111000001011011011011010 (
1'
b10010101110001 &
1%
0$
b10010101110001 #
0"
0!
$end
#5
1$
#10
0%
0$
#15
1$
#20
b1 5
b1100000111000001011011011011010 6
0$
#25
1$
#30
1"
b10 5
b110000011100000101101101101101 6
0$
#35
1$
#40
0"
b11 5
b11000001110000010110110110110 6
0$
#45
1$
#50
1"
b100 5
b1100000111000001011011011011 6
0$
#55
1$
#60
b101 5
b110000011100000101101101101 6
0$
#65
1$
#70
0"
b110 5
b11000001110000010110110110 6
0$
#75
1$
#80
1"
b111 5
b1100000111000001011011011 6
0$
#85
1$
#90
b1000 5
b110000011100000101101101 6
0$
#95
1$
#100
0"
b1001 5
b11000001110000010110110 6
0$
#105
1$
#110
1"
b1010 5
b1100000111000001011011 6
0$
#115
1$
#120
b1011 5
b110000011100000101101 6
0$
#125
1$
#130
0"
b1100 5
b11000001110000010110 6
0$
#135
1$
#140
1"
b1101 5
b1100000111000001011 6
0$
#145
1$
#150
b1110 5
b110000011100000101 6
0$
#155
1$
#160
0"
b1111 5
b11000001110000010 6
0$
#165
1$
#170
1"
b10000 5
b1100000111000001 6
0$
#175
1$
#180
0"
b10001 5
b110000011100000 6
0$
#185
1$
#190
b10010 5
b11000001110000 6
0$
#195
1$
#200
b10011 5
b1100000111000 6
0$
#205
1$
#210
b10100 5
b110000011100 6
0$
#215
1$
#220
b10101 5
b11000001110 6
0$
#225
1$
#230
1"
b10110 5
b1100000111 6
0$
#235
1$
#240
b10111 5
b110000011 6
0$
#245
1$
#250
b11000 5
b11000001 6
0$
#255
1$
#260
0"
b11001 5
b1100000 6
0$
#265
1$
#270
b11010 5
b110000 6
0$
#275
1$
#280
b11011 5
b11000 6
0$
#285
1$
#290
b11100 5
b1100 6
0$
#295
1$
#300
b11101 5
b110 6
0$
#305
1$
#310
1"
b11110 5
b11 6
0$
#315
1$
#320
1!
b11111 5
b1 6
0$
#325
1$
#330
0"
0!
b100000 5
b0 6
0$
#335
1$
#340
b0 5
0$
#345
1$
#350
b1 5
b1100000111000001011011011011010 6
0$
#355
1$
#360
1"
b10 5
b110000011100000101101101101101 6
0$
#365
1$
#370
0"
b11 5
b11000001110000010110110110110 6
0$
#375
1$
#380
1"
b100 5
b1100000111000001011011011011 6
0$
#385
1$
#390
b101 5
b110000011100000101101101101 6
0$
#395
1$
#400
0"
b110 5
b11000001110000010110110110 6
0$
#405
1$
#410
1"
b111 5
b1100000111000001011011011 6
0$
#415
1$
#420
b1000 5
b110000011100000101101101 6
0$
#425
1$
#430
0"
b1001 5
b11000001110000010110110 6
0$
#435
1$
#440
1"
b1010 5
b1100000111000001011011 6
0$
#445
1$
#450
b1011 5
b110000011100000101101 6
0$
#455
1$
#460
0"
b1100 5
b11000001110000010110 6
0$
#465
1$
#470
1"
b1101 5
b1100000111000001011 6
0$
#475
1$
#480
b1110 5
b110000011100000101 6
0$
#485
1$
#490
0"
b1111 5
b11000001110000010 6
0$
#495
1$
#500
1"
b10000 5
b1100000111000001 6
0$
#505
1$
#510
0"
b10001 5
b110000011100000 6
0$
#515
1$
#520
b10010 5
b11000001110000 6
0$
#525
1$
#530
b10011 5
b1100000111000 6
0$
#535
1$
#540
b10100 5
b110000011100 6
0$
#545
1$
#550
b10101 5
b11000001110 6
0$
#555
1$
#560
1"
b10110 5
b1100000111 6
0$
#565
1$
#570
b10111 5
b110000011 6
0$
#575
1$
#580
b11000 5
b11000001 6
0$
#585
1$
#590
0"
b11001 5
b1100000 6
0$
#595
1$
#600
b11010 5
b110000 6
0$
#605
1$
#610
b11011 5
b11000 6
0$
#615
1$
#620
b11100 5
b1100 6
0$
#625
1$
#630
b11101 5
b110 6
0$
#635
1$
#640
1"
b11110 5
b11 6
0$
#645
1$
#650
1!
b11111 5
b1 6
0$
#655
1$
#660
0"
0!
b100000 5
b0 6
0$
#665
1$
#670
b0 5
0$
#675
1$
#680
b1 5
b1100000111000001011011011011010 6
0$
#685
1$
#690
1"
b10 5
b110000011100000101101101101101 6
0$
#695
1$
#700
0"
b11 5
b11000001110000010110110110110 6
0$
#705
1$
#710
1"
b100 5
b1100000111000001011011011011 6
0$
#715
1$
#720
b101 5
b110000011100000101101101101 6
0$
#725
1$
#730
0"
b110 5
b11000001110000010110110110 6
0$
#735
1$
#740
1"
b111 5
b1100000111000001011011011 6
0$
#745
1$
#750
b1000 5
b110000011100000101101101 6
0$
#755
1$
#760
0"
b1001 5
b11000001110000010110110 6
0$
#765
1$
#770
1"
b1010 5
b1100000111000001011011 6
0$
#775
1$
#780
b1011 5
b110000011100000101101 6
0$
#785
1$
#790
0"
b1100 5
b11000001110000010110 6
0$
#795
1$
#800
1"
b1101 5
b1100000111000001011 6
0$
#805
1$
#810
b1110 5
b110000011100000101 6
0$
#815
1$
#820
0"
b1111 5
b11000001110000010 6
0$
#825
1$
#830
1"
b10000 5
b1100000111000001 6
0$
#835
1$
#840
0"
b10001 5
b110000011100000 6
0$
#845
1$
#850
b10010 5
b11000001110000 6
0$
#855
1$
#860
b10011 5
b1100000111000 6
0$
#865
1$
#870
b10100 5
b110000011100 6
0$
#875
1$
#880
b10101 5
b11000001110 6
0$
#885
1$
#890
1"
b10110 5
b1100000111 6
0$
#895
1$
#900
b10111 5
b110000011 6
0$
#905
1$
#910
b11000 5
b11000001 6
0$
#915
1$
#920
0"
b11001 5
b1100000 6
0$
#925
1$
#930
b11010 5
b110000 6
0$
#935
1$
#940
b11011 5
b11000 6
0$
#945
1$
#950
b11100 5
b1100 6
0$
#955
1$
#960
b11101 5
b110 6
0$
#965
1$
#970
1"
b11110 5
b11 6
0$
#975
1$
#980
1!
b11111 5
b1 6
0$
#985
1$
#990
0"
0!
b100000 5
b0 6
0$
#995
1$
#1000
b0 5
0$
#1005
1$
#1010
b1 5
b1100000111000001011011011011010 6
0$
#1015
1$
#1020
1"
b10 5
b110000011100000101101101101101 6
0$
#1025
1$
#1030
0"
b11 5
b11000001110000010110110110110 6
0$
#1035
1$
#1040
1"
b100 5
b1100000111000001011011011011 6
0$
#1045
1$
#1050
b101 5
b110000011100000101101101101 6
0$
#1055
1$
#1060
0"
b110 5
b11000001110000010110110110 6
0$
#1065
1$
#1070
1"
b111 5
b1100000111000001011011011 6
0$
#1075
1$
#1080
b1000 5
b110000011100000101101101 6
0$
#1085
1$
#1090
0"
b1001 5
b11000001110000010110110 6
0$
#1095
1$
#1100
1"
b1010 5
b1100000111000001011011 6
0$
#1105
1$
#1110
b1011 5
b110000011100000101101 6
0$
#1115
1$
#1120
0"
b1100 5
b11000001110000010110 6
0$
#1125
1$
#1130
1"
b1101 5
b1100000111000001011 6
0$
#1135
1$
#1140
b1110 5
b110000011100000101 6
0$
#1145
1$
#1150
0"
b1111 5
b11000001110000010 6
0$
#1155
1$
#1160
1"
b10000 5
b1100000111000001 6
0$
#1165
1$
#1170
0"
b10001 5
b110000011100000 6
0$
#1175
1$
#1180
b10010 5
b11000001110000 6
0$
#1185
1$
#1190
b10011 5
b1100000111000 6
0$
#1195
1$
#1200
b10100 5
b110000011100 6
0$
#1205
1$
#1210
b10101 5
b11000001110 6
0$
#1215
1$
#1220
1"
b10110 5
b1100000111 6
0$
#1225
1$
#1230
b10111 5
b110000011 6
0$
#1235
1$
#1240
b11000 5
b11000001 6
0$
#1245
1$
#1250
0"
b11001 5
b1100000 6
0$
#1255
1$
#1260
b11010 5
b110000 6
0$
#1265
1$
#1270
b11011 5
b11000 6
0$
#1275
1$
#1280
b11100 5
b1100 6
0$
#1285
1$
#1290
b11101 5
b110 6
0$
#1295
1$
#1300
1"
b11110 5
b11 6
0$
#1305
1$
#1310
1!
b11111 5
b1 6
0$
#1315
1$
#1320
0"
0!
b100000 5
b0 6
0$
#1325
1$
#1330
b0 5
0$
#1335
1$
#1340
b1 5
b1100000111000001011011011011010 6
0$
#1345
1$
#1350
1"
b10 5
b110000011100000101101101101101 6
0$
#1355
1$
#1360
0"
b11 5
b11000001110000010110110110110 6
0$
#1365
1$
#1370
1"
b100 5
b1100000111000001011011011011 6
0$
#1375
1$
#1380
b101 5
b110000011100000101101101101 6
0$
#1385
1$
#1390
0"
b110 5
b11000001110000010110110110 6
0$
#1395
1$
#1400
1"
b111 5
b1100000111000001011011011 6
0$
#1405
1$
#1410
b1000 5
b110000011100000101101101 6
0$
#1415
1$
#1420
0"
b1001 5
b11000001110000010110110 6
0$
#1425
1$
#1430
1"
b1010 5
b1100000111000001011011 6
0$
#1435
1$
#1440
b1011 5
b110000011100000101101 6
0$
#1445
1$
#1450
0"
b1100 5
b11000001110000010110 6
0$
#1455
1$
#1460
1"
b1101 5
b1100000111000001011 6
0$
#1465
1$
#1470
b1110 5
b110000011100000101 6
0$
#1475
1$
#1480
0"
b1111 5
b11000001110000010 6
0$
#1485
1$
#1490
1"
b10000 5
b1100000111000001 6
0$
#1495
1$
#1500
0"
b10001 5
b110000011100000 6
0$
#1505
1$
#1510
b10010 5
b11000001110000 6
0$
#1515
1$
#1520
b10011 5
b1100000111000 6
0$
#1525
1$
#1530
b10100 5
b110000011100 6
0$
#1535
1$
#1540
b10101 5
b11000001110 6
0$
#1545
1$
#1550
1"
b10110 5
b1100000111 6
0$
#1555
1$
#1560
b10111 5
b110000011 6
0$
#1565
1$
#1570
b11000 5
b11000001 6
0$
#1575
1$
#1580
0"
b11001 5
b1100000 6
0$
#1585
1$
#1590
b11010 5
b110000 6
0$
#1595
1$
#1600
b11011 5
b11000 6
0$
#1605
1$
#1610
b11100 5
b1100 6
0$
#1615
1$
#1620
b11101 5
b110 6
0$
#1625
1$
#1630
1"
b11110 5
b11 6
0$
#1635
1$
#1640
1!
b11111 5
b1 6
0$
#1645
1$
#1650
0"
0!
b100000 5
b0 6
0$
#1655
1$
#1660
b0 5
0$
#1665
1$
#1670
b1 5
b1100000111000001011011011011010 6
0$
#1675
1$
#1680
1"
b10 5
b110000011100000101101101101101 6
0$
#1685
1$
#1690
0"
b11 5
b11000001110000010110110110110 6
0$
#1695
1$
#1700
1"
b100 5
b1100000111000001011011011011 6
0$
#1705
1$
#1710
b101 5
b110000011100000101101101101 6
0$
#1715
1$
#1720
0"
b110 5
b11000001110000010110110110 6
0$
#1725
1$
#1730
1"
b111 5
b1100000111000001011011011 6
0$
#1735
1$
#1740
b1000 5
b110000011100000101101101 6
0$
#1745
1$
#1750
0"
b1001 5
b11000001110000010110110 6
0$
#1755
1$
#1760
1"
b1010 5
b1100000111000001011011 6
0$
#1765
1$
#1770
b1011 5
b110000011100000101101 6
0$
#1775
1$
#1780
0"
b1100 5
b11000001110000010110 6
0$
#1785
1$
#1790
1"
b1101 5
b1100000111000001011 6
0$
#1795
1$
#1800
b1110 5
b110000011100000101 6
0$
#1805
1$
#1810
0"
b1111 5
b11000001110000010 6
0$
#1815
1$
#1820
1"
b10000 5
b1100000111000001 6
0$
#1825
1$
#1830
0"
b10001 5
b110000011100000 6
0$
#1835
1$
#1840
b10010 5
b11000001110000 6
0$
#1845
1$
#1850
b10011 5
b1100000111000 6
0$
#1855
1$
#1860
b10100 5
b110000011100 6
0$
#1865
1$
#1870
b10101 5
b11000001110 6
0$
#1875
1$
#1880
1"
b10110 5
b1100000111 6
0$
#1885
1$
#1890
b10111 5
b110000011 6
0$
#1895
1$
#1900
b11000 5
b11000001 6
0$
#1905
1$
#1910
0"
b11001 5
b1100000 6
0$
#1915
1$
#1920
b11010 5
b110000 6
0$
#1925
1$
#1930
b11011 5
b11000 6
0$
#1935
1$
#1940
b11100 5
b1100 6
0$
#1945
1$
#1950
b11101 5
b110 6
0$
#1955
1$
#1960
1"
b11110 5
b11 6
0$
#1965
1$
#1970
1!
b11111 5
b1 6
0$
#1975
1$
#1980
0"
0!
b100000 5
b0 6
0$
#1985
1$
#1990
b0 5
0$
#1995
1$
#2000
b1 5
b1100000111000001011011011011010 6
0$
#2005
1$
#2010
1"
b10 5
b110000011100000101101101101101 6
0$
#2015
1$
#2020
0"
b11 5
b11000001110000010110110110110 6
0$
#2025
1$
#2030
1"
b100 5
b1100000111000001011011011011 6
0$
#2035
1$
#2040
b101 5
b110000011100000101101101101 6
0$
#2045
1$
#2050
0"
b110 5
b11000001110000010110110110 6
0$
#2055
1$
#2060
1"
b111 5
b1100000111000001011011011 6
0$
#2065
1$
#2070
b1000 5
b110000011100000101101101 6
0$
#2075
1$
#2080
0"
b1001 5
b11000001110000010110110 6
0$
#2085
1$
#2090
1"
b1010 5
b1100000111000001011011 6
0$
#2095
1$
#2100
b1011 5
b110000011100000101101 6
0$
#2105
1$
#2110
0"
b1100 5
b11000001110000010110 6
0$
#2115
1$
#2120
1"
b1101 5
b1100000111000001011 6
0$
#2125
1$
#2130
b1110 5
b110000011100000101 6
0$
#2135
1$
#2140
0"
b1111 5
b11000001110000010 6
0$
#2145
1$
#2150
1"
b10000 5
b1100000111000001 6
0$
#2155
1$
#2160
0"
b10001 5
b110000011100000 6
0$
#2165
1$
#2170
b10010 5
b11000001110000 6
0$
#2175
1$
#2180
b10011 5
b1100000111000 6
0$
#2185
1$
#2190
b10100 5
b110000011100 6
0$
#2195
1$
#2200
b10101 5
b11000001110 6
0$
#2205
1$
#2210
1"
b10110 5
b1100000111 6
0$
#2215
1$
#2220
b10111 5
b110000011 6
0$
#2225
1$
#2230
b11000 5
b11000001 6
0$
#2235
1$
#2240
0"
b11001 5
b1100000 6
0$
#2245
1$
#2250
b11010 5
b110000 6
0$
#2255
1$
#2260
b11011 5
b11000 6
0$
#2265
1$
#2270
b11100 5
b1100 6
0$
#2275
1$
#2280
b11101 5
b110 6
0$
#2285
1$
#2290
1"
b11110 5
b11 6
0$
#2295
1$
#2300
1!
b11111 5
b1 6
0$
#2305
1$
#2310
0"
0!
b100000 5
b0 6
0$
#2315
1$
#2320
b0 5
0$
#2325
1$
#2330
b1 5
b1100000111000001011011011011010 6
0$
#2335
1$
#2340
1"
b10 5
b110000011100000101101101101101 6
0$
#2345
1$
#2350
0"
b11 5
b11000001110000010110110110110 6
0$
#2355
1$
#2360
1"
b100 5
b1100000111000001011011011011 6
0$
#2365
1$
#2370
b101 5
b110000011100000101101101101 6
0$
#2375
1$
#2380
0"
b110 5
b11000001110000010110110110 6
0$
#2385
1$
#2390
1"
b111 5
b1100000111000001011011011 6
0$
#2395
1$
#2400
b1000 5
b110000011100000101101101 6
0$
#2405
1$
#2410
0"
b1001 5
b11000001110000010110110 6
0$
#2415
1$
#2420
1"
b1010 5
b1100000111000001011011 6
0$
#2425
1$
#2430
b1011 5
b110000011100000101101 6
0$
#2435
1$
#2440
0"
b1100 5
b11000001110000010110 6
0$
#2445
1$
#2450
1"
b1101 5
b1100000111000001011 6
0$
#2455
1$
#2460
b1110 5
b110000011100000101 6
0$
#2465
1$
#2470
0"
b1111 5
b11000001110000010 6
0$
#2475
1$
#2480
1"
b10000 5
b1100000111000001 6
0$
#2485
1$
#2490
0"
b10001 5
b110000011100000 6
0$
#2495
1$
#2500
b10010 5
b11000001110000 6
0$
#2505
1$
#2510
b10011 5
b1100000111000 6
0$
#2515
1$
#2520
b10100 5
b110000011100 6
0$
#2525
1$
#2530
b10101 5
b11000001110 6
0$
#2535
1$
#2540
1"
b10110 5
b1100000111 6
0$
#2545
1$
#2550
b10111 5
b110000011 6
0$
#2555
1$
#2560
b11000 5
b11000001 6
0$
#2565
1$
#2570
0"
b11001 5
b1100000 6
0$
#2575
1$
#2580
b11010 5
b110000 6
0$
#2585
1$
#2590
b11011 5
b11000 6
0$
#2595
1$
#2600
b11100 5
b1100 6
0$
#2605
1$
#2610
b11101 5
b110 6
0$
#2615
1$
#2620
1"
b11110 5
b11 6
0$
#2625
1$
#2630
1!
b11111 5
b1 6
0$
#2635
1$
#2640
0"
0!
b100000 5
b0 6
0$
#2645
1$
#2650
b0 5
0$
#2655
1$
#2660
b1 5
b1100000111000001011011011011010 6
0$
#2665
1$
#2670
1"
b10 5
b110000011100000101101101101101 6
0$
#2675
1$
#2680
0"
b11 5
b11000001110000010110110110110 6
0$
#2685
1$
#2690
1"
b100 5
b1100000111000001011011011011 6
0$
#2695
1$
#2700
b101 5
b110000011100000101101101101 6
0$
#2705
1$
#2710
0"
b110 5
b11000001110000010110110110 6
0$
#2715
1$
#2720
1"
b111 5
b1100000111000001011011011 6
0$
#2725
1$
#2730
b1000 5
b110000011100000101101101 6
0$
#2735
1$
#2740
0"
b1001 5
b11000001110000010110110 6
0$
#2745
1$
#2750
1"
b1010 5
b1100000111000001011011 6
0$
#2755
1$
#2760
b1011 5
b110000011100000101101 6
0$
#2765
1$
#2770
0"
b1100 5
b11000001110000010110 6
0$
#2775
1$
#2780
1"
b1101 5
b1100000111000001011 6
0$
#2785
1$
#2790
b1110 5
b110000011100000101 6
0$
#2795
1$
#2800
0"
b1111 5
b11000001110000010 6
0$
#2805
1$
#2810
1"
b10000 5
b1100000111000001 6
0$
#2815
1$
#2820
0"
b10001 5
b110000011100000 6
0$
#2825
1$
#2830
b10010 5
b11000001110000 6
0$
#2835
1$
#2840
b10011 5
b1100000111000 6
0$
#2845
1$
#2850
b10100 5
b110000011100 6
0$
#2855
1$
#2860
b10101 5
b11000001110 6
0$
#2865
1$
#2870
1"
b10110 5
b1100000111 6
0$
#2875
1$
#2880
b10111 5
b110000011 6
0$
#2885
1$
#2890
b11000 5
b11000001 6
0$
#2895
1$
#2900
0"
b11001 5
b1100000 6
0$
#2905
1$
#2910
b11010 5
b110000 6
0$
#2915
1$
#2920
b11011 5
b11000 6
0$
#2925
1$
#2930
b11100 5
b1100 6
0$
#2935
1$
#2940
b11101 5
b110 6
0$
#2945
1$
#2950
1"
b11110 5
b11 6
0$
#2955
1$
#2960
1!
b11111 5
b1 6
0$
#2965
1$
#2970
0"
0!
b100000 5
b0 6
0$
#2975
1$
#2980
b0 5
0$
#2985
1$
#2990
b1 5
b1100000111000001011011011011010 6
0$
#2995
1$
#3000
1"
b10 5
b110000011100000101101101101101 6
0$
#3005
1$
#3010
0"
b11 5
b11000001110000010110110110110 6
0$
#3015
1$
#3020
1"
b100 5
b1100000111000001011011011011 6
0$
#3025
1$
#3030
b101 5
b110000011100000101101101101 6
0$
#3035
1$
#3040
0"
b110 5
b11000001110000010110110110 6
0$
#3045
1$
#3050
1"
b111 5
b1100000111000001011011011 6
0$
#3055
1$
#3060
b1000 5
b110000011100000101101101 6
0$
#3065
1$
#3070
0"
b1001 5
b11000001110000010110110 6
0$
#3075
1$
#3080
1"
b1010 5
b1100000111000001011011 6
0$
#3085
1$
#3090
b1011 5
b110000011100000101101 6
0$
#3095
1$
#3100
0"
b1100 5
b11000001110000010110 6
0$
#3105
1$
#3110
1"
b1101 5
b1100000111000001011 6
0$
#3115
1$
#3120
b1110 5
b110000011100000101 6
0$
#3125
1$
#3130
0"
b1111 5
b11000001110000010 6
0$
#3135
1$
#3140
1"
b10000 5
b1100000111000001 6
0$
#3145
1$
#3150
0"
b10001 5
b110000011100000 6
0$
#3155
1$
#3160
b10010 5
b11000001110000 6
0$
#3165
1$
#3170
b10011 5
b1100000111000 6
0$
#3175
1$
#3180
b10100 5
b110000011100 6
0$
#3185
1$
#3190
b10101 5
b11000001110 6
0$
#3195
1$
#3200
1"
b10110 5
b1100000111 6
0$
#3205
1$
#3210
b10111 5
b110000011 6
0$
#3215
1$
#3220
b11000 5
b11000001 6
0$
#3225
1$
#3230
0"
b11001 5
b1100000 6
0$
#3235
1$
#3240
b11010 5
b110000 6
0$
#3245
1$
#3250
b11011 5
b11000 6
0$
#3255
1$
#3260
b11100 5
b1100 6
0$
#3265
1$
#3270
b11101 5
b110 6
0$
#3275
1$
#3280
1"
b11110 5
b11 6
0$
#3285
1$
#3290
1!
b11111 5
b1 6
0$
#3295
1$
#3300
0"
0!
b100000 5
b0 6
0$
#3305
1$
#3310
b0 5
0$
#3315
1$
#3320
b1 5
b1100000111000001011011011011010 6
0$
#3325
1$
#3330
1"
b10 5
b110000011100000101101101101101 6
0$
#3335
1$
#3340
0"
b11 5
b11000001110000010110110110110 6
0$
#3345
1$
#3350
1"
b100 5
b1100000111000001011011011011 6
0$
#3355
1$
#3360
b101 5
b110000011100000101101101101 6
0$
#3365
1$
#3370
0"
b110 5
b11000001110000010110110110 6
0$
#3375
1$
#3380
1"
b111 5
b1100000111000001011011011 6
0$
#3385
1$
#3390
b1000 5
b110000011100000101101101 6
0$
#3395
1$
#3400
0"
b1001 5
b11000001110000010110110 6
0$
#3405
1$
#3410
1"
b1010 5
b1100000111000001011011 6
0$
#3415
1$
#3420
b1011 5
b110000011100000101101 6
0$
#3425
1$
#3430
0"
b1100 5
b11000001110000010110 6
0$
#3435
1$
#3440
1"
b1101 5
b1100000111000001011 6
0$
#3445
1$
#3450
b1110 5
b110000011100000101 6
0$
#3455
1$
#3460
0"
b1111 5
b11000001110000010 6
0$
#3465
1$
#3470
1"
b10000 5
b1100000111000001 6
0$
#3475
1$
#3480
0"
b10001 5
b110000011100000 6
0$
#3485
1$
#3490
b10010 5
b11000001110000 6
0$
#3495
1$
#3500
b10011 5
b1100000111000 6
0$
#3505
1$
#3510
b10100 5
b110000011100 6
0$
#3515
1$
#3520
b10101 5
b11000001110 6
0$
#3525
1$
#3530
1"
b10110 5
b1100000111 6
0$
#3535
1$
#3540
b10111 5
b110000011 6
0$
#3545
1$
#3550
b11000 5
b11000001 6
0$
#3555
1$
#3560
0"
b11001 5
b1100000 6
0$
#3565
1$
#3570
b11010 5
b110000 6
0$
#3575
1$
#3580
b11011 5
b11000 6
0$
#3585
1$
#3590
b11100 5
b1100 6
0$
#3595
1$
#3600
b11101 5
b110 6
0$
#3605
1$
#3610
1"
b11110 5
b11 6
0$
#3615
1$
#3620
1!
b11111 5
b1 6
0$
#3625
1$
#3630
0"
0!
b100000 5
b0 6
0$
#3635
1$
#3640
b0 5
0$
#3645
1$
#3650
b1 5
b1100000111000001011011011011010 6
0$
#3655
1$
#3660
1"
b10 5
b110000011100000101101101101101 6
0$
#3665
1$
#3670
0"
b11 5
b11000001110000010110110110110 6
0$
#3675
1$
#3680
1"
b100 5
b1100000111000001011011011011 6
0$
#3685
1$
#3690
b101 5
b110000011100000101101101101 6
0$
#3695
1$
#3700
0"
b110 5
b11000001110000010110110110 6
0$
#3705
1$
#3710
1"
b111 5
b1100000111000001011011011 6
0$
#3715
1$
#3720
b1000 5
b110000011100000101101101 6
0$
#3725
1$
#3730
0"
b1001 5
b11000001110000010110110 6
0$
#3735
1$
#3740
1"
b1010 5
b1100000111000001011011 6
0$
#3745
1$
#3750
b1011 5
b110000011100000101101 6
0$
#3755
1$
#3760
0"
b1100 5
b11000001110000010110 6
0$
#3765
1$
#3770
1"
b1101 5
b1100000111000001011 6
0$
#3775
1$
#3780
b1110 5
b110000011100000101 6
0$
#3785
1$
#3790
0"
b1111 5
b11000001110000010 6
0$
#3795
1$
#3800
1"
b10000 5
b1100000111000001 6
0$
#3805
1$
#3810
0"
b10001 5
b110000011100000 6
0$
#3815
1$
#3820
b10010 5
b11000001110000 6
0$
#3825
1$
#3830
b10011 5
b1100000111000 6
0$
#3835
1$
#3840
b10100 5
b110000011100 6
0$
#3845
1$
#3850
b10101 5
b11000001110 6
0$
#3855
1$
#3860
1"
b10110 5
b1100000111 6
0$
#3865
1$
#3870
b10111 5
b110000011 6
0$
#3875
1$
#3880
b11000 5
b11000001 6
0$
#3885
1$
#3890
0"
b11001 5
b1100000 6
0$
#3895
1$
#3900
b11010 5
b110000 6
0$
#3905
1$
#3910
b11011 5
b11000 6
0$
#3915
1$
#3920
b11100 5
b1100 6
0$
#3925
1$
#3930
b11101 5
b110 6
0$
#3935
1$
#3940
1"
b11110 5
b11 6
0$
#3945
1$
#3950
1!
b11111 5
b1 6
0$
#3955
1$
#3960
0"
0!
b100000 5
b0 6
0$
#3965
1$
#3970
b0 5
0$
#3975
1$
#3980
b1 5
b1100000111000001011011011011010 6
0$
#3985
1$
#3990
1"
b10 5
b110000011100000101101101101101 6
0$
#3995
1$
#4000
0"
b11 5
b11000001110000010110110110110 6
0$
#4005
1$
#4010
1"
b100 5
b1100000111000001011011011011 6
0$
#4015
1$
#4020
b101 5
b110000011100000101101101101 6
0$
#4025
1$
#4030
0"
b110 5
b11000001110000010110110110 6
0$
#4035
1$
#4040
1"
b111 5
b1100000111000001011011011 6
0$
#4045
1$
#4050
b1000 5
b110000011100000101101101 6
0$
#4055
1$
#4060
0"
b1001 5
b11000001110000010110110 6
0$
#4065
1$
#4070
1"
b1010 5
b1100000111000001011011 6
0$
#4075
1$
#4080
b1011 5
b110000011100000101101 6
0$
#4085
1$
#4090
0"
b1100 5
b11000001110000010110 6
0$
#4095
1$
#4100
1"
b1101 5
b1100000111000001011 6
0$
#4105
1$
#4110
b1110 5
b110000011100000101 6
0$
#4115
1$
#4120
0"
b1111 5
b11000001110000010 6
0$
#4125
1$
#4130
1"
b10000 5
b1100000111000001 6
0$
#4135
1$
#4140
0"
b10001 5
b110000011100000 6
0$
#4145
1$
#4150
b10010 5
b11000001110000 6
0$
#4155
1$
#4160
b10011 5
b1100000111000 6
0$
#4165
1$
#4170
b10100 5
b110000011100 6
0$
#4175
1$
#4180
b10101 5
b11000001110 6
0$
#4185
1$
#4190
1"
b10110 5
b1100000111 6
0$
#4195
1$
#4200
b10111 5
b110000011 6
0$
#4205
1$
#4210
b11000 5
b11000001 6
0$
#4215
1$
#4220
0"
b11001 5
b1100000 6
0$
#4225
1$
#4230
b11010 5
b110000 6
0$
#4235
1$
#4240
b11011 5
b11000 6
0$
