display_out.v
module display_out
(    input wire clk,
    input wire rst,
    input wire enable,
    input wire [15:0] bcd_in,
    input wire [31:0] segment_data,
    output wire data_out,
    output wire sending_data
);

//assign clk = HF_int_osc;


// Conversor BSD a 32 bits en segment_data


// Paralelo a Serie de 32 bits

parameter [31:0] send_interval = 31'd32;
reg [31:0] interval_counter;
reg [31:0] segment_data_out;

always @(negedge clk)
    if (rst) begin
        interval_counter <= 0;
        segment_data_out <= 0; 
    end else if (enable) begin
        if (interval_counter == 0)
            segment_data_out <= segment_data;
        else 
            segment_data_out <= segment_data_out >> 1;

        if (interval_counter <= send_interval)
            interval_counter <= interval_counter + 1;
        else   
            interval_counter <= 0;
        
    end

assign sending_data = (interval_counter == 31);
assign data_out = segment_data_out[0];

endmodule

display_tb.v


module dispout_tb();
    reg clk;
    reg reset;
    reg [15:0] bcd_in;
    reg [31:0] segment_data;
    wire ser_clk, ser_data, data_ready, disp_clk;
    display_out disp1(clk, reset, 1'd1, bcd_in, segment_data, data_out, sending_data);

    initial begin
        clk <= 0;
        reset <= 1;
        bcd_in <= 16'b0010010101110001; 
        segment_data <= 32'b11000000111110000011111100001111;
    end


    always begin
        #5 clk = ~clk;
    end

    initial begin
        $dumpfile("1.vcd");
        $dumpvars(2);
        #10 reset <= 0;

        #9000 $finish;
    end


endmodule

1.vcd
$date
	Thu Oct 23 21:53:36 2025
$end
$version
	Icarus Verilog
$end
$timescale
	1s
$end
$scope module dispout_tb $end
$var wire 1 ! sending_data $end
$var wire 1 " data_out $end
$var reg 16 # bcd_in [15:0] $end
$var reg 1 $ clk $end
$var reg 1 % reset $end
$var reg 32 & segment_data [31:0] $end
$scope module disp1 $end
$var wire 16 ' bcd_in [15:0] $end
$var wire 1 $ clk $end
$var wire 1 ( enable $end
$var wire 1 % rst $end
$var wire 32 ) segment_data [31:0] $end
$var wire 1 ! sending_data $end
$var wire 1 " data_out $end
$var parameter 32 * send_interval $end
$var reg 32 + interval_counter [31:0] $end
$var reg 32 , segment_data_out [31:0] $end
$upscope $end
$upscope $end
$enddefinitions $end
$comment Show the parameter values. $end
$dumpall
b100000 *
$end
#0
$dumpvars
b0 ,
b0 +
b11000000111110000011111100001111 )
1(
b10010101110001 '
b11000000111110000011111100001111 &
1%
0$
b10010101110001 #
0"
0!
$end
#5
1$
#10
0%
0$
#15
1$
#20
1"
b1 +
b11000000111110000011111100001111 ,
0$
#25
1$
#30
b10 +
b1100000011111000001111110000111 ,
0$
#35
1$
#40
b11 +
b110000001111100000111111000011 ,
0$
#45
1$
#50
b100 +
b11000000111110000011111100001 ,
0$
#55
1$
#60
0"
b101 +
b1100000011111000001111110000 ,
0$
#65
1$
#70
b110 +
b110000001111100000111111000 ,
0$
#75
1$
#80
b111 +
b11000000111110000011111100 ,
0$
#85
1$
#90
b1000 +
b1100000011111000001111110 ,
0$
#95
1$
#100
1"
b1001 +
b110000001111100000111111 ,
0$
#105
1$
#110
b1010 +
b11000000111110000011111 ,
0$
#115
1$
#120
b1011 +
b1100000011111000001111 ,
0$
#125
1$
#130
b1100 +
b110000001111100000111 ,
0$
#135
1$
#140
b1101 +
b11000000111110000011 ,
0$
#145
1$
#150
b1110 +
b1100000011111000001 ,
0$
#155
1$
#160
0"
b1111 +
b110000001111100000 ,
0$
#165
1$
#170
b10000 +
b11000000111110000 ,
0$
#175
1$
#180
b10001 +
b1100000011111000 ,
0$
#185
1$
#190
b10010 +
b110000001111100 ,
0$
#195
1$
#200
b10011 +
b11000000111110 ,
0$
#205
1$
#210
1"
b10100 +
b1100000011111 ,
0$
#215
1$
#220
b10101 +
b110000001111 ,
0$
#225
1$
#230
b10110 +
b11000000111 ,
0$
#235
1$
#240
b10111 +
b1100000011 ,
0$
#245
1$
#250
b11000 +
b110000001 ,
0$
#255
1$
#260
0"
b11001 +
b11000000 ,
0$
#265
1$
#270
b11010 +
b1100000 ,
0$
#275
1$
#280
b11011 +
b110000 ,
0$
#285
1$
#290
b11100 +
b11000 ,
0$
#295
1$
#300
b11101 +
b1100 ,
0$
#305
1$
#310
b11110 +
b110 ,
0$
#315
1$
#320
1"
1!
b11111 +
b11 ,
0$
#325
1$
#330
0!
b100000 +
b1 ,
0$
#335
1$
#340
0"
b100001 +
b0 ,
0$
#345
1$
#350
b0 +
0$
#355
1$
#360
1"
b1 +
b11000000111110000011111100001111 ,
0$
#365
1$
#370
b10 +
b1100000011111000001111110000111 ,
0$
#375
1$
#380
b11 +
b110000001111100000111111000011 ,
0$
#385
1$
#390
b100 +
b11000000111110000011111100001 ,
0$
#395
1$
#400
0"
b101 +
b1100000011111000001111110000 ,
0$
#405
1$
#410
b110 +
b110000001111100000111111000 ,
0$
#415
1$
#420
b111 +
b11000000111110000011111100 ,
0$
#425
1$
#430
b1000 +
b1100000011111000001111110 ,
0$
#435
1$
#440
1"
b1001 +
b110000001111100000111111 ,
0$
#445
1$
#450
b1010 +
b11000000111110000011111 ,
0$
#455
1$
#460
b1011 +
b1100000011111000001111 ,
0$
#465
1$
#470
b1100 +
b110000001111100000111 ,
0$
#475
1$
#480
b1101 +
b11000000111110000011 ,
0$
#485
1$
#490
b1110 +
b1100000011111000001 ,
0$
#495
1$
#500
0"
b1111 +
b110000001111100000 ,
0$
#505
1$
#510
b10000 +
b11000000111110000 ,
0$
#515
1$
#520
b10001 +
b1100000011111000 ,
0$
#525
1$
#530
b10010 +
b110000001111100 ,
0$
#535
1$
#540
b10011 +
b11000000111110 ,
0$
#545
1$
#550
1"
b10100 +
b1100000011111 ,
0$
#555
1$
#560
b10101 +
b110000001111 ,
0$
#565
1$
#570
b10110 +
b11000000111 ,
0$
#575
1$
#580
b10111 +
b1100000011 ,
0$
#585
1$
#590
b11000 +
b110000001 ,
0$
#595
1$
#600
0"
b11001 +
b11000000 ,
0$
#605
1$
#610
b11010 +
b1100000 ,
0$
#615
1$
#620
b11011 +
b110000 ,
0$
#625
1$
#630
b11100 +
b11000 ,
0$
#635
1$
#640
b11101 +
b1100 ,
0$
#645
1$
#650
b11110 +
b110 ,
0$
#655
1$
#660
1"
1!
b11111 +
b11 ,
0$
#665
1$
#670
0!
b100000 +
b1 ,
0$
#675
1$
#680
0"
b100001 +
b0 ,
0$
#685
1$
#690
b0 +
0$
#695
1$
#700
1"
b1 +
b11000000111110000011111100001111 ,
0$
#705
1$
#710
b10 +
b1100000011111000001111110000111 ,
0$
#715
1$
#720
b11 +
b110000001111100000111111000011 ,
0$
#725
1$
#730
b100 +
b11000000111110000011111100001 ,
0$
#735
1$
#740
0"
b101 +
b1100000011111000001111110000 ,
0$
#745
1$
#750
b110 +
b110000001111100000111111000 ,
0$
#755
1$
#760
b111 +
b11000000111110000011111100 ,
0$
#765
1$
#770
b1000 +
b1100000011111000001111110 ,
0$
#775
1$
#780
1"
b1001 +
b110000001111100000111111 ,
0$
#785
1$
#790
b1010 +
b11000000111110000011111 ,
0$
#795
1$
#800
b1011 +
b1100000011111000001111 ,
0$
#805
1$
#810
b1100 +
b110000001111100000111 ,
0$
#815
1$
#820
b1101 +
b11000000111110000011 ,
0$
#825
1$
#830
b1110 +
b1100000011111000001 ,
0$
#835
1$
#840
0"
b1111 +
b110000001111100000 ,
0$
#845
1$
#850
b10000 +
b11000000111110000 ,
0$
#855
1$
#860
b10001 +
b1100000011111000 ,
0$
#865
1$
#870
b10010 +
b110000001111100 ,
0$
#875
1$
#880
b10011 +
b11000000111110 ,
0$
#885
1$
#890
1"
b10100 +
b1100000011111 ,
0$
#895
1$
#900
b10101 +
b110000001111 ,
0$
#905
1$
#910
b10110 +
b11000000111 ,
0$
#915
1$
#920
b10111 +
b1100000011 ,
0$
#925
1$
#930
b11000 +
b110000001 ,
0$
#935
1$
#940
0"
b11001 +
b11000000 ,
0$
#945
1$
#950
b11010 +
b1100000 ,
0$
#955
1$
#960
b11011 +
b110000 ,
0$
#965
1$
#970
b11100 +
b11000 ,
0$
#975
1$
#980
b11101 +
b1100 ,
0$
#985
1$
#990
b11110 +
b110 ,
0$
#995
1$
#1000
1"
1!
b11111 +
b11 ,
0$
#1005
1$
#1010
0!
b100000 +
b1 ,
0$
#1015
1$
#1020
0"
b100001 +
b0 ,
0$
#1025
1$
#1030
b0 +
0$
#1035
1$
#1040
1"
b1 +
b11000000111110000011111100001111 ,
0$
#1045
1$
#1050
b10 +
b1100000011111000001111110000111 ,
0$
#1055
1$
#1060
b11 +
b110000001111100000111111000011 ,
0$
#1065
1$
#1070
b100 +
b11000000111110000011111100001 ,
0$
#1075
1$
#1080
0"
b101 +
b1100000011111000001111110000 ,
0$
#1085
1$
#1090
b110 +
b110000001111100000111111000 ,
0$
#1095
1$
#1100
b111 +
b11000000111110000011111100 ,
0$
#1105
1$
#1110
b1000 +
b1100000011111000001111110 ,
0$
#1115
1$
#1120
1"
b1001 +
b110000001111100000111111 ,
0$
#1125
1$
#1130
b1010 +
b11000000111110000011111 ,
0$
#1135
1$
#1140
b1011 +
b1100000011111000001111 ,
0$
#1145
1$
#1150
b1100 +
b110000001111100000111 ,
0$
#1155
1$
#1160
b1101 +
b11000000111110000011 ,
0$
#1165
1$
#1170
b1110 +
b1100000011111000001 ,
0$
#1175
1$
#1180
0"
b1111 +
b110000001111100000 ,
0$
#1185
1$
#1190
b10000 +
b11000000111110000 ,
0$
#1195
1$
#1200
b10001 +
b1100000011111000 ,
0$
#1205
1$
#1210
b10010 +
b110000001111100 ,
0$
#1215
1$
#1220
b10011 +
b11000000111110 ,
0$
#1225
1$
#1230
1"
b10100 +
b1100000011111 ,
0$
#1235
1$
#1240
b10101 +
b110000001111 ,
0$
#1245
1$
#1250
b10110 +
b11000000111 ,
0$
#1255
1$
#1260
b10111 +
b1100000011 ,
0$
#1265
1$
#1270
b11000 +
b110000001 ,
0$
#1275
1$
#1280
0"
b11001 +
b11000000 ,
0$
#1285
1$
#1290
b11010 +
b1100000 ,
0$
#1295
1$
#1300
b11011 +
b110000 ,
0$
#1305
1$
#1310
b11100 +
b11000 ,
0$
#1315
1$
#1320
b11101 +
b1100 ,
0$
#1325
1$
#1330
b11110 +
b110 ,
0$
#1335
1$
#1340
1"
1!
b11111 +
b11 ,
0$
#1345
1$
#1350
0!
b100000 +
b1 ,
0$
#1355
1$
#1360
0"
b100001 +
b0 ,
0$
#1365
1$
#1370
b0 +
0$
#1375
1$
#1380
1"
b1 +
b11000000111110000011111100001111 ,
0$
#1385
1$
#1390
b10 +
b1100000011111000001111110000111 ,
0$
#1395
1$
#1400
b11 +
b110000001111100000111111000011 ,
0$
#1405
1$
#1410
b100 +
b11000000111110000011111100001 ,
0$
#1415
1$
#1420
0"
b101 +
b1100000011111000001111110000 ,
0$
#1425
1$
#1430
b110 +
b110000001111100000111111000 ,
0$
#1435
1$
#1440
b111 +
b11000000111110000011111100 ,
0$
#1445
1$
#1450
b1000 +
b1100000011111000001111110 ,
0$
#1455
1$
#1460
1"
b1001 +
b110000001111100000111111 ,
0$
#1465
1$
#1470
b1010 +
b11000000111110000011111 ,
0$
#1475
1$
#1480
b1011 +
b1100000011111000001111 ,
0$
#1485
1$
#1490
b1100 +
b110000001111100000111 ,
0$
#1495
1$
#1500
b1101 +
b11000000111110000011 ,
0$
#1505
1$
#1510
b1110 +
b1100000011111000001 ,
0$
#1515
1$
#1520
0"
b1111 +
b110000001111100000 ,
0$
#1525
1$
#1530
b10000 +
b11000000111110000 ,
0$
#1535
1$
#1540
b10001 +
b1100000011111000 ,
0$
#1545
1$
#1550
b10010 +
b110000001111100 ,
0$
#1555
1$
#1560
b10011 +
b11000000111110 ,
0$
#1565
1$
#1570
1"
b10100 +
b1100000011111 ,
0$
#1575
1$
#1580
b10101 +
b110000001111 ,
0$
#1585
1$
#1590
b10110 +
b11000000111 ,
0$
#1595
1$
#1600
b10111 +
b1100000011 ,
0$
#1605
1$
#1610
b11000 +
b110000001 ,
0$
#1615
1$
#1620
0"
b11001 +
b11000000 ,
0$
#1625
1$
#1630
b11010 +
b1100000 ,
0$
#1635
1$
#1640
b11011 +
b110000 ,
0$
#1645
1$
#1650
b11100 +
b11000 ,
0$
#1655
1$
#1660
b11101 +
b1100 ,
0$
#1665
1$
#1670
b11110 +
b110 ,
0$
#1675
1$
#1680
1"
1!
b11111 +
b11 ,
0$
#1685
1$
#1690
0!
b100000 +
b1 ,
0$
#1695
1$
#1700
0"
b100001 +
b0 ,
0$
#1705
1$
#1710
b0 +
0$
#1715
1$
#1720
1"
b1 +
b11000000111110000011111100001111 ,
0$
#1725
1$
#1730
b10 +
b1100000011111000001111110000111 ,
0$
#1735
1$
#1740
b11 +
b110000001111100000111111000011 ,
0$
#1745
1$
#1750
b100 +
b11000000111110000011111100001 ,
0$
#1755
1$
#1760
0"
b101 +
b1100000011111000001111110000 ,
0$
#1765
1$
#1770
b110 +
b110000001111100000111111000 ,
0$
#1775
1$
#1780
b111 +
b11000000111110000011111100 ,
0$
#1785
1$
#1790
b1000 +
b1100000011111000001111110 ,
0$
#1795
1$
#1800
1"
b1001 +
b110000001111100000111111 ,
0$
#1805
1$
#1810
b1010 +
b11000000111110000011111 ,
0$
#1815
1$
#1820
b1011 +
b1100000011111000001111 ,
0$
#1825
1$
#1830
b1100 +
b110000001111100000111 ,
0$
#1835
1$
#1840
b1101 +
b11000000111110000011 ,
0$
#1845
1$
#1850
b1110 +
b1100000011111000001 ,
0$
#1855
1$
#1860
0"
b1111 +
b110000001111100000 ,
0$
#1865
1$
#1870
b10000 +
b11000000111110000 ,
0$
#1875
1$
#1880
b10001 +
b1100000011111000 ,
0$
#1885
1$
#1890
b10010 +
b110000001111100 ,
0$
#1895
1$
#1900
b10011 +
b11000000111110 ,
0$
#1905
1$
#1910
1"
b10100 +
b1100000011111 ,
0$
#1915
1$
#1920
b10101 +
b110000001111 ,
0$
#1925
1$
#1930
b10110 +
b11000000111 ,
0$
#1935
1$
#1940
b10111 +
b1100000011 ,
0$
#1945
1$
#1950
b11000 +
b110000001 ,
0$
#1955
1$
#1960
0"
b11001 +
b11000000 ,
0$
#1965
1$
#1970
b11010 +
b1100000 ,
0$
#1975
1$
#1980
b11011 +
b110000 ,
0$
#1985
1$
#1990
b11100 +
b11000 ,
0$
#1995
1$
#2000
b11101 +
b1100 ,
0$
#2005
1$
#2010
b11110 +
b110 ,
0$
#2015
1$
#2020
1"
1!
b11111 +
b11 ,
0$
#2025
1$
#2030
0!
b100000 +
b1 ,
0$
#2035
1$
#2040
0"
b100001 +
b0 ,
0$
#2045
1$
#2050
b0 +
0$
#2055
1$
#2060
1"
b1 +
b11000000111110000011111100001111 ,
0$
#2065
1$
#2070
b10 +
b1100000011111000001111110000111 ,
0$
#2075
1$
#2080
b11 +
b110000001111100000111111000011 ,
0$
#2085
1$
#2090
b100 +
b11000000111110000011111100001 ,
0$
#2095
1$
#2100
0"
b101 +
b1100000011111000001111110000 ,
0$
#2105
1$
#2110
b110 +
b110000001111100000111111000 ,
0$
#2115
1$
#2120
b111 +
b11000000111110000011111100 ,
0$
#2125
1$
#2130
b1000 +
b1100000011111000001111110 ,
0$
#2135
1$
#2140
1"
b1001 +
b110000001111100000111111 ,
0$
#2145
1$
#2150
b1010 +
b11000000111110000011111 ,
0$
#2155
1$
#2160
b1011 +
b1100000011111000001111 ,
0$
#2165
1$
#2170
b1100 +
b110000001111100000111 ,
0$
#2175
1$
#2180
b1101 +
b11000000111110000011 ,
0$
#2185
1$
#2190
b1110 +
b1100000011111000001 ,
0$
#2195
1$
#2200
0"
b1111 +
b110000001111100000 ,
0$
#2205
1$
#2210
b10000 +
b11000000111110000 ,
0$
#2215
1$
#2220
b10001 +
b1100000011111000 ,
0$
#2225
1$
#2230
b10010 +
b110000001111100 ,
0$
#2235
1$
#2240
b10011 +
b11000000111110 ,
0$
#2245
1$
#2250
1"
b10100 +
b1100000011111 ,
0$
#2255
1$
#2260
b10101 +
b110000001111 ,
0$
#2265
1$
#2270
b10110 +
b11000000111 ,
0$
#2275
1$
#2280
b10111 +
b1100000011 ,
0$
#2285
1$
#2290
b11000 +
b110000001 ,
0$
#2295
1$
#2300
0"
b11001 +
b11000000 ,
0$
#2305
1$
#2310
b11010 +
b1100000 ,
0$
#2315
1$
#2320
b11011 +
b110000 ,
0$
#2325
1$
#2330
b11100 +
b11000 ,
0$
#2335
1$
#2340
b11101 +
b1100 ,
0$
#2345
1$
#2350
b11110 +
b110 ,
0$
#2355
1$
#2360
1"
1!
b11111 +
b11 ,
0$
#2365
1$
#2370
0!
b100000 +
b1 ,
0$
#2375
1$
#2380
0"
b100001 +
b0 ,
0$
#2385
1$
#2390
b0 +
0$
#2395
1$
#2400
1"
b1 +
b11000000111110000011111100001111 ,
0$
#2405
1$
#2410
b10 +
b1100000011111000001111110000111 ,
0$
#2415
1$
#2420
b11 +
b110000001111100000111111000011 ,
0$
#2425
1$
#2430
b100 +
b11000000111110000011111100001 ,
0$
#2435
1$
#2440
0"
b101 +
b1100000011111000001111110000 ,
0$
#2445
1$
#2450
b110 +
b110000001111100000111111000 ,
0$
#2455
1$
#2460
b111 +
b11000000111110000011111100 ,
0$
#2465
1$
#2470
b1000 +
b1100000011111000001111110 ,
0$
#2475
1$
#2480
1"
b1001 +
b110000001111100000111111 ,
0$
#2485
1$
#2490
b1010 +
b11000000111110000011111 ,
0$
#2495
1$
#2500
b1011 +
b1100000011111000001111 ,
0$
#2505
1$
#2510
b1100 +
b110000001111100000111 ,
0$
#2515
1$
#2520
b1101 +
b11000000111110000011 ,
0$
#2525
1$
#2530
b1110 +
b1100000011111000001 ,
0$
#2535
1$
#2540
0"
b1111 +
b110000001111100000 ,
0$
#2545
1$
#2550
b10000 +
b11000000111110000 ,
0$
#2555
1$
#2560
b10001 +
b1100000011111000 ,
0$
#2565
1$
#2570
b10010 +
b110000001111100 ,
0$
#2575
1$
#2580
b10011 +
b11000000111110 ,
0$
#2585
1$
#2590
1"
b10100 +
b1100000011111 ,
0$
#2595
1$
#2600
b10101 +
b110000001111 ,
0$
#2605
1$
#2610
b10110 +
b11000000111 ,
0$
#2615
1$
#2620
b10111 +
b1100000011 ,
0$
#2625
1$
#2630
b11000 +
b110000001 ,
0$
#2635
1$
#2640
0"
b11001 +
b11000000 ,
0$
#2645
1$
#2650
b11010 +
b1100000 ,
0$
#2655
1$
#2660
b11011 +
b110000 ,
0$
#2665
1$
#2670
b11100 +
b11000 ,
0$
#2675
1$
#2680
b11101 +
b1100 ,
0$
#2685
1$
#2690
b11110 +
b110 ,
0$
#2695
1$
#2700
1"
1!
b11111 +
b11 ,
0$
#2705
1$
#2710
0!
b100000 +
b1 ,
0$
#2715
1$
#2720
0"
b100001 +
b0 ,
0$
#2725
1$
#2730
b0 +
0$
#2735
1$
#2740
1"
b1 +
b11000000111110000011111100001111 ,
0$
#2745
1$
#2750
b10 +
b1100000011111000001111110000111 ,
0$
#2755
1$
#2760
b11 +
b110000001111100000111111000011 ,
0$
#2765
1$
#2770
b100 +
b11000000111110000011111100001 ,
0$
#2775
1$
#2780
0"
b101 +
b1100000011111000001111110000 ,
0$
#2785
1$
#2790
b110 +
b110000001111100000111111000 ,
0$
#2795
1$
#2800
b111 +
b11000000111110000011111100 ,
0$
#2805
1$
#2810
b1000 +
b1100000011111000001111110 ,
0$
#2815
1$
#2820
1"
b1001 +
b110000001111100000111111 ,
0$
#2825
1$
#2830
b1010 +
b11000000111110000011111 ,
0$
#2835
1$
#2840
b1011 +
b1100000011111000001111 ,
0$
#2845
1$
#2850
b1100 +
b110000001111100000111 ,
0$
#2855
1$
#2860
b1101 +
b11000000111110000011 ,
0$
#2865
1$
#2870
b1110 +
b1100000011111000001 ,
0$
#2875
1$
#2880
0"
b1111 +
b110000001111100000 ,
0$
#2885
1$
#2890
b10000 +
b11000000111110000 ,
0$
#2895
1$
#2900
b10001 +
b1100000011111000 ,
0$
#2905
1$
#2910
b10010 +
b110000001111100 ,
0$
#2915
1$
#2920
b10011 +
b11000000111110 ,
0$
#2925
1$
#2930
1"
b10100 +
b1100000011111 ,
0$
#2935
1$
#2940
b10101 +
b110000001111 ,
0$
#2945
1$
#2950
b10110 +
b11000000111 ,
0$
#2955
1$
#2960
b10111 +
b1100000011 ,
0$
#2965
1$
#2970
b11000 +
b110000001 ,
0$
#2975
1$
#2980
0"
b11001 +
b11000000 ,
0$
#2985
1$
#2990
b11010 +
b1100000 ,
0$
#2995
1$
#3000
b11011 +
b110000 ,
0$
#3005
1$
#3010
b11100 +
b11000 ,
0$
#3015
1$
#3020
b11101 +
b1100 ,
0$
#3025
1$
#3030
b11110 +
b110 ,
0$
#3035
1$
#3040
1"
1!
b11111 +
b11 ,
0$
#3045
1$
#3050
0!
b100000 +
b1 ,
0$
#3055
1$
#3060
0"
b100001 +
b0 ,
0$
#3065
1$
#3070
b0 +
0$
#3075
1$
#3080
1"
b1 +
b11000000111110000011111100001111 ,
0$
#3085
1$
#3090
b10 +
b1100000011111000001111110000111 ,
0$
#3095
1$
#3100
b11 +
b110000001111100000111111000011 ,
0$
#3105
1$
#3110
b100 +
b11000000111110000011111100001 ,
0$
#3115
1$
#3120
0"
b101 +
b1100000011111000001111110000 ,
0$
#3125
1$
#3130
b110 +
b110000001111100000111111000 ,
0$
#3135
1$
#3140
b111 +
b11000000111110000011111100 ,
0$
#3145
1$
#3150
b1000 +
b1100000011111000001111110 ,
0$
#3155
1$
#3160
1"
b1001 +
b110000001111100000111111 ,
0$
#3165
1$
#3170
b1010 +
b11000000111110000011111 ,
0$
#3175
1$
#3180
b1011 +
b1100000011111000001111 ,
0$
#3185
1$
#3190
b1100 +
b110000001111100000111 ,
0$
#3195
1$
#3200
b1101 +
b11000000111110000011 ,
0$
#3205
1$
#3210
b1110 +
b1100000011111000001 ,
0$
#3215
1$
#3220
0"
b1111 +
b110000001111100000 ,
0$
#3225
1$
#3230
b10000 +
b11000000111110000 ,
0$
#3235
1$
#3240
b10001 +
b1100000011111000 ,
0$
#3245
1$
#3250
b10010 +
b110000001111100 ,
0$
#3255
1$
#3260
b10011 +
b11000000111110 ,
0$
#3265
1$
#3270
1"
b10100 +
b1100000011111 ,
0$
#3275
1$
#3280
b10101 +
b110000001111 ,
0$
#3285
1$
#3290
b10110 +
b11000000111 ,
0$
#3295
1$
#3300
b10111 +
b1100000011 ,
0$
#3305
1$
#3310
b11000 +
b110000001 ,
0$
#3315
1$
#3320
0"
b11001 +
b11000000 ,
0$
#3325
1$
#3330
b11010 +
b1100000 ,
0$
#3335
1$
#3340
b11011 +
b110000 ,
0$
#3345
1$
#3350
b11100 +
b11000 ,
0$
#3355
1$
#3360
b11101 +
b1100 ,
0$
#3365
1$
#3370
b11110 +
b110 ,
0$
#3375
1$
#3380
1"
1!
b11111 +
b11 ,
0$
#3385
1$
#3390
0!
b100000 +
b1 ,
0$
#3395
1$
#3400
0"
b100001 +
b0 ,
0$
#3405
1$
#3410
b0 +
0$
#3415
1$
#3420
1"
b1 +
b11000000111110000011111100001111 ,
0$
#3425
1$
#3430
b10 +
b1100000011111000001111110000111 ,
0$
#3435
1$
#3440
b11 +
b110000001111100000111111000011 ,
0$
#3445
1$
#3450
b100 +
b11000000111110000011111100001 ,
0$
#3455
1$
#3460
0"
b101 +
b1100000011111000001111110000 ,
0$
#3465
1$
#3470
b110 +
b110000001111100000111111000 ,
0$
#3475
1$
#3480
b111 +
b11000000111110000011111100 ,
0$
#3485
1$
#3490
b1000 +
b1100000011111000001111110 ,
0$
#3495
1$
#3500
1"
b1001 +
b110000001111100000111111 ,
0$
#3505
1$
#3510
b1010 +
b11000000111110000011111 ,
0$
#3515
1$
#3520
b1011 +
b1100000011111000001111 ,
0$
#3525
1$
#3530
b1100 +
b110000001111100000111 ,
0$
#3535
1$
#3540
b1101 +
b11000000111110000011 ,
0$
#3545
1$
#3550
b1110 +
b1100000011111000001 ,
0$
#3555
1$
#3560
0"
b1111 +
b110000001111100000 ,
0$
#3565
1$
#3570
b10000 +
b11000000111110000 ,
0$
#3575
1$
#3580
b10001 +
b1100000011111000 ,
0$
#3585
1$
#3590
b10010 +
b110000001111100 ,
0$
#3595
1$
#3600
b10011 +
b11000000111110 ,
0$
#3605
1$
#3610
1"
b10100 +
b1100000011111 ,
0$
#3615
1$
#3620
b10101 +
b110000001111 ,
0$
#3625
1$
#3630
b10110 +
b11000000111 ,
0$
#3635
1$
#3640
b10111 +
b1100000011 ,
0$
#3645
1$
#3650
b11000 +
b110000001 ,
0$
#3655
1$
#3660
0"
b11001 +
b11000000 ,
0$
#3665
1$
#3670
b11010 +
b1100000 ,
0$
#3675
1$
#3680
b11011 +
b110000 ,
0$
#3685
1$
#3690
b11100 +
b11000 ,
0$
#3695
1$
#3700
b11101 +
b1100 ,
0$
#3705
1$
#3710
b11110 +
b110 ,
0$
#3715
1$
#3720
1"
1!
b11111 +
b11 ,
0$
#3725
1$
#3730
0!
b100000 +
b1 ,
0$
#3735
1$
#3740
0"
b100001 +
b0 ,
0$
#3745
1$
#3750
b0 +
0$
#3755
1$
#3760
1"
b1 +
b11000000111110000011111100001111 ,
0$
#3765
1$
#3770
b10 +
b1100000011111000001111110000111 ,
0$
#3775
1$
#3780
b11 +
b110000001111100000111111000011 ,
0$
#3785
1$
#3790
b100 +
b11000000111110000011111100001 ,
0$
#3795
1$
#3800
0"
b101 +
b1100000011111000001111110000 ,
0$
#3805
1$
#3810
b110 +
b110000001111100000111111000 ,
0$
#3815
1$
#3820
b111 +
b11000000111110000011111100 ,
0$
#3825
1$
#3830
b1000 +
b1100000011111000001111110 ,
0$
#3835
1$
#3840
1"
b1001 +
b110000001111100000111111 ,
0$
#3845
1$
#3850
b1010 +
b11000000111110000011111 ,
0$
#3855
1$
#3860
b1011 +
b1100000011111000001111 ,
0$
#3865
1$
#3870
b1100 +
b110000001111100000111 ,
0$
#3875
1$
#3880
b1101 +
b11000000111110000011 ,
0$
#3885
1$
#3890
b1110 +
b1100000011111000001 ,
0$
#3895
1$
#3900
0"
b1111 +
b110000001111100000 ,
0$
#3905
1$
#3910
b10000 +
b11000000111110000 ,
0$
#3915
1$
#3920
b10001 +
b1100000011111000 ,
0$
#3925
1$
#3930
b10010 +
b110000001111100 ,
0$
#3935
1$
#3940
b10011 +
b11000000111110 ,
0$
#3945
1$
#3950
1"
b10100 +
b1100000011111 ,
0$
#3955
1$
#3960
b10101 +
b110000001111 ,
0$
#3965
1$
#3970
b10110 +
b11000000111 ,
0$
#3975
1$
#3980
b10111 +
b1100000011 ,
0$
#3985
1$
#3990
b11000 +
b110000001 ,
0$
#3995
1$
#4000
0"
b11001 +
b11000000 ,
0$
#4005
1$
#4010
b11010 +
b1100000 ,
0$
#4015
1$
#4020
b11011 +
b110000 ,
0$
#4025
1$
#4030
b11100 +
b11000 ,
0$
#4035
1$
#4040
b11101 +
b1100 ,
0$
#4045
1$
#4050
b11110 +
b110 ,
0$
#4055
1$
#4060
1"
1!
b11111 +
b11 ,
0$
#4065
1$
#4070
0!
b100000 +
b1 ,
0$
#4075
1$
#4080
0"
b100001 +
b0 ,
0$
#4085
1$
#4090
b0 +
0$
#4095
1$
#4100
1"
b1 +
b11000000111110000011111100001111 ,
0$
#4105
1$
#4110
b10 +
b1100000011111000001111110000111 ,
0$
#4115
1$
#4120
b11 +
b110000001111100000111111000011 ,
0$
#4125
1$
#4130
b100 +
b11000000111110000011111100001 ,
0$
#4135
1$
#4140
0"
b101 +
b1100000011111000001111110000 ,
0$
#4145
1$
#4150
b110 +
b110000001111100000111111000 ,
0$
#4155
1$
#4160
b111 +
b11000000111110000011111100 ,
0$
#4165
1$
#4170
b1000 +
b1100000011111000001111110 ,
0$
#4175
1$
#4180
1"
b1001 +
b110000001111100000111111 ,
0$
#4185
1$
#4190
b1010 +
b11000000111110000011111 ,
0$
#4195
1$
#4200
b1011 +
b1100000011111000001111 ,
0$
#4205
1$
#4210
b1100 +
b110000001111100000111 ,
0$
#4215
1$
#4220
b1101 +
b11000000111110000011 ,
0$
#4225
1$
#4230
b1110 +
b1100000011111000001 ,
0$
#4235
1$
#4240
0"
b1111 +
b110000001111100000 ,
0$
#4245
1$
#4250
b10000 +
b11000000111110000 ,
0$
#4255
1$
#4260
b10001 +
b1100000011111000 ,
0$
#4265
1$
#4270
b10010 +
b110000001111100 ,
0$
#4275
1$
#4280
b10011 +
b11000000111110 ,
0$
#4285
1$
#4290
1"
b10100 +
b1100000011111 ,
0$
#4295
1$
#4300
b10101 +
b110000001111 ,
0$
#4305
1$
#4310
b10110 +
b11000000111 ,
0$
#4315
1$
#4320
b10111 +
b1100000011 ,
0$
#4325
1$
#4330
b11000 +
b110000001 ,
0$
#4335
1$
#4340
0"
b11001 +
b11000000 ,
0$
#4345
1$
#4350
b11010 +
b1100000 ,
0$
#4355
1$
#4360
b11011 +
b110000 ,
0$
#4365
1$
#4370
b11100 +
b11000 ,
0$
#4375
1$
#4380
b11101 +
b1100 ,
0$
#4385
1$
#4390
b11110 +
b110 ,
0$
#4395
1$
#4400
1"
1!
b11111 +
b11 ,
0$
#4405
1$
#4410
0!
b100000 +
b1 ,
0$
#4415
1$
#4420
0"
b100001 +
b0 ,
0$
#4425
1$
#4430
b0 +
0$
#4435
1$
#4440
1"
b1 +
b11000000111110000011111100001111 ,
0$
#4445
1$
#4450
b10 +
b1100000011111000001111110000111 ,
0$
#4455
1$
#4460
b11 +
b110000001111100000111111000011 ,
0$
#4465
1$
#4470
b100 +
b11000000111110000011111100001 ,
0$
#4475
1$
#4480
0"
b101 +
b1100000011111000001111110000 ,
0$
#4485
1$
#4490
b110 +
b110000001111100000111111000 ,
0$
#4495
1$
#4500
b111 +
b11000000111110000011111100 ,
0$
#4505
1$
#4510
b1000 +
b1100000011111000001111110 ,
0$
#4515
1$
